<Properties StartupConfiguration="{0E420B7C-6E87-4433-AE65-B61B8A15CB4C}|Default">
  <MonoDevelop.Ide.ItemProperties.June17thExamples.IntroToOOP PreferredExecutionTarget="MonoDevelop.Default" />
  <MonoDevelop.Ide.ItemProperties.June14ThExamples.LINQExamples PreferredExecutionTarget="MonoDevelop.Default" />
  <MonoDevelop.Ide.ItemProperties.June6thArrays.IntroArrays PreferredExecutionTarget="MonoDevelop.Default" />
  <MonoDevelop.Ide.ItemProperties.June16thExamples.ErrorHandlingExamples PreferredExecutionTarget="MonoDevelop.Default" />
  <MonoDevelop.Ide.ItemProperties.June2ndMethods.Methods PreferredExecutionTarget="MonoDevelop.Default" />
  <MonoDevelop.Ide.Workbench>
    <Files>
      <File FileName="ClassesAndObjects/Program.cs" Line="40" Column="33" />
      <File FileName="ClassesAndObjects/Pen.cs" Line="4" Column="2" />
    </Files>
    <Pads>
      <Pad Id="ProjectPad">
        <State name="__root__">
          <Node name="AHBC_DOTNET_MAY_2021" expanded="True">
            <Node name="June21stExamples" expanded="True">
              <Node name="ClassesAndObjects" expanded="True">
                <Node name="Book.cs" selected="True" />
              </Node>
            </Node>
          </Node>
        </State>
      </Pad>
    </Pads>
  </MonoDevelop.Ide.Workbench>
  <MonoDevelop.Ide.ItemProperties.June21stExamples.ClassesAndObjects PreferredExecutionTarget="MonoDevelop.Default" />
  <MonoDevelop.Ide.DebuggingService.PinnedWatches />
  <MonoDevelop.Ide.ItemProperties.May25thIntroduction.HelloWorld PreferredExecutionTarget="MonoDevelop.Default" />
  <DisabledProjects>
    <String>AHBC_DOTNET_MAY_2021/AHBC_DOTNET_MAY_2021.csproj</String>
  </DisabledProjects>
  <MonoDevelop.Ide.Workspace ActiveConfiguration="Debug" />
  <MonoDevelop.Ide.ItemProperties.May26ThLoopIntro.Loops PreferredExecutionTarget="MonoDevelop.Default" />
  <MonoDevelop.Ide.DebuggingService.Breakpoints>
    <BreakpointStore>
      <Breakpoint file="/Users/darionthompson/Desktop/Grand_Circus/AHBC_DOTNET_MAY_2021/ErrorHandlingExamples/Program.cs" relfile="ErrorHandlingExamples/Program.cs" line="15" column="1" />
      <Breakpoint file="/Users/darionthompson/Desktop/Grand_Circus/AHBC_DOTNET_MAY_2021/ErrorHandlingExamples/Program.cs" relfile="ErrorHandlingExamples/Program.cs" line="35" column="1" />
      <Breakpoint file="/Users/darionthompson/Desktop/Grand_Circus/AHBC_DOTNET_MAY_2021/ErrorHandlingExamples/Program.cs" relfile="ErrorHandlingExamples/Program.cs" line="41" column="1" />
      <Breakpoint file="/Users/darionthompson/Desktop/Grand_Circus/AHBC_DOTNET_MAY_2021/ErrorHandlingExamples/Program.cs" relfile="ErrorHandlingExamples/Program.cs" line="66" column="1" />
      <Breakpoint file="/Users/darionthompson/Desktop/Grand_Circus/AHBC_DOTNET_MAY_2021/IntroToOOP/Cars.cs" relfile="IntroToOOP/Cars.cs" line="23" column="1" />
      <Breakpoint file="/Users/darionthompson/Desktop/Grand_Circus/AHBC_DOTNET_MAY_2021/IntroToOOP/Program.cs" relfile="IntroToOOP/Program.cs" line="63" column="1" />
      <Breakpoint file="/Users/darionthompson/Desktop/Grand_Circus/AHBC_DOTNET_MAY_2021/ClassesAndObjects/Book.cs" relfile="ClassesAndObjects/Book.cs" line="26" column="1" />
    </BreakpointStore>
  </MonoDevelop.Ide.DebuggingService.Breakpoints>
  <MultiItemStartupConfigurations />
  <MonoDevelop.Ide.ItemProperties.June3rdStrings.StringsExample PreferredExecutionTarget="MonoDevelop.Default" />
</Properties>